agents/__init__.py
agents/arxiv_agent.py
agents/shell_agent.py
odyagent2409-0.1.2.dist-info/METADATA
odyagent2409-0.1.2.dist-info/WHEEL
odyagent2409-0.1.2.dist-info/entry_points.txt
odyagent2409-0.1.2.dist-info/top_level.txt
odyagent2409-0.1.2.dist-info/RECORD
